mcp_config_manager/__init__.py
mcp_config_manager-0.1.1.dist-info/METADATA
mcp_config_manager-0.1.1.dist-info/WHEEL
mcp_config_manager-0.1.1.dist-info/licenses/LICENSE
mcp_config_manager-0.1.1.dist-info/RECORD
