Metadata-Version: 2.4
Name: mcp-config-manager
Version: 0.1.1
Summary: Configuration management utilities for MCP servers
Project-URL: Homepage, https://github.com/easytocloud/mcp-config-manager
Project-URL: Repository, https://github.com/easytocloud/mcp-config-manager.git
Author-email: easytoclaude <erik@easytocloud.com>
License-Expression: MIT
License-File: LICENSE
Keywords: claude,cline,configuration,mcp
Classifier: Development Status :: 3 - Alpha
Classifier: Intended Audience :: Developers
Classifier: License :: OSI Approved :: MIT License
Classifier: Programming Language :: Python :: 3
Classifier: Programming Language :: Python :: 3.10
Classifier: Programming Language :: Python :: 3.11
Requires-Python: >=3.10
